jupyterlabs_sql_codemirror/__init__.py
jupyterlabs_sql_codemirror/_version.py
jupyterlabs_sql_codemirror/labextension/package.json
jupyterlabs_sql_codemirror/labextension/static/568.1b7e284a99798f5bca3e.js
jupyterlabs_sql_codemirror/labextension/static/747.a859a2fa420a10cde27f.js
jupyterlabs_sql_codemirror/labextension/static/794.2810971233953f0c230c.js
jupyterlabs_sql_codemirror/labextension/static/remoteEntry.e6db867d13ca79d1959d.js
jupyterlabs_sql_codemirror/labextension/static/style.js
jupyterlabs_sql_codemirror/labextension/static/third-party-licenses.json
jupyterlabs_sql_codemirror-0.1.4.data/data/share/jupyter/labextensions/@composable/jupyterlabs-sql-codemirror/install.json
jupyterlabs_sql_codemirror-0.1.4.data/data/share/jupyter/labextensions/@composable/jupyterlabs-sql-codemirror/package.json
jupyterlabs_sql_codemirror-0.1.4.data/data/share/jupyter/labextensions/@composable/jupyterlabs-sql-codemirror/static/568.1b7e284a99798f5bca3e.js
jupyterlabs_sql_codemirror-0.1.4.data/data/share/jupyter/labextensions/@composable/jupyterlabs-sql-codemirror/static/747.a859a2fa420a10cde27f.js
jupyterlabs_sql_codemirror-0.1.4.data/data/share/jupyter/labextensions/@composable/jupyterlabs-sql-codemirror/static/794.2810971233953f0c230c.js
jupyterlabs_sql_codemirror-0.1.4.data/data/share/jupyter/labextensions/@composable/jupyterlabs-sql-codemirror/static/remoteEntry.e6db867d13ca79d1959d.js
jupyterlabs_sql_codemirror-0.1.4.data/data/share/jupyter/labextensions/@composable/jupyterlabs-sql-codemirror/static/style.js
jupyterlabs_sql_codemirror-0.1.4.data/data/share/jupyter/labextensions/@composable/jupyterlabs-sql-codemirror/static/third-party-licenses.json
jupyterlabs_sql_codemirror-0.1.4.dist-info/LICENSE
jupyterlabs_sql_codemirror-0.1.4.dist-info/METADATA
jupyterlabs_sql_codemirror-0.1.4.dist-info/WHEEL
jupyterlabs_sql_codemirror-0.1.4.dist-info/top_level.txt
jupyterlabs_sql_codemirror-0.1.4.dist-info/RECORD
