Metadata-Version: 2.1
Name: jupyterlabs-sql-codemirror
Version: 0.1.4
Summary: For highlighting with sql magic commands.
Home-page: https://github.com/surdouski/jupyterlabs_sql_codemirror
Author: Michael Surdouski
License: BSD-3-Clause
Keywords: Jupyter,JupyterLab
Platform: Linux
Platform: Mac OS X
Platform: Windows
Classifier: License :: OSI Approved :: BSD License
Classifier: Programming Language :: Python
Classifier: Programming Language :: Python :: 3
Classifier: Programming Language :: Python :: 3.6
Classifier: Programming Language :: Python :: 3.7
Classifier: Programming Language :: Python :: 3.8
Classifier: Framework :: Jupyter
Classifier: Framework :: Jupyter :: JupyterLab :: 3
Classifier: Framework :: Jupyter :: JupyterLab :: Extensions
Classifier: Framework :: Jupyter :: JupyterLab :: Extensions :: Prebuilt
Classifier: Framework :: Jupyter :: JupyterLab :: Extensions :: Themes
Requires-Python: >=3.7
License-File: LICENSE
Requires-Dist: jupyterlab (~=3.1)
